dotc/__init__.py
dotc/__main__.py
dotc/dotc.py
dotc/inc/json/dict_tracy.json
dotc-0.4.2.dist-info/licenses/LICENSE
dotc-0.4.2.dist-info/METADATA
dotc-0.4.2.dist-info/WHEEL
dotc-0.4.2.dist-info/entry_points.txt
dotc-0.4.2.dist-info/top_level.txt
dotc-0.4.2.dist-info/RECORD
