Metadata-Version: 2.4
Name: dotc
Version: 0.4.2
Summary: DOTC (like Yahtzee) - Access Nested Dicts and Lists via Dots
Author-email: Mike Steele <mike@mikesteele.us>
License: MIT License
Project-URL: Homepage, https://github.com/soulrx/dotc
Keywords: nested,dot,dict,list,datastructure,dotspace,dotdict,dotlist,xml,dotc
Classifier: License :: OSI Approved :: MIT License
Classifier: Programming Language :: Python
Classifier: Programming Language :: Python :: 3
Requires-Python: >=3.9
License-File: LICENSE
Provides-Extra: dev
Requires-Dist: bumpver; extra == "dev"
Requires-Dist: build; extra == "dev"
Requires-Dist: twine; extra == "dev"
Requires-Dist: wheel; extra == "dev"
Requires-Dist: setuptools; extra == "dev"
Dynamic: license-file
